setup.py
Package/__init__.py
Package/app.py
Package/feature_extractor.py
Package/main.py
Package/model1.py
Package/model2.py
Package/model3.py
servierpck.egg-info/PKG-INFO
servierpck.egg-info/SOURCES.txt
servierpck.egg-info/dependency_links.txt
servierpck.egg-info/not-zip-safe
servierpck.egg-info/top_level.txt